riscvlib/__init__.py
riscvlib/instruction.py
riscvlib/riscvdata.py
riscvlib/utils.py
tests/__init__.py
tests/test_instructions.py
riscvlib-0.7.5.dist-info/LICENSE
riscvlib-0.7.5.dist-info/METADATA
riscvlib-0.7.5.dist-info/WHEEL
riscvlib-0.7.5.dist-info/top_level.txt
riscvlib-0.7.5.dist-info/RECORD
