Metadata-Version: 2.1
Name: riscvlib
Version: 0.7.5
Summary: Resources for working with RISC-V in Python
Home-page: https://github.com/Mike451/riscvlib
Author: Mike Harris
Author-email: mike.harris451@gmail.com
Classifier: Programming Language :: Python :: 3
Classifier: License :: OSI Approved :: MIT License
Classifier: Operating System :: OS Independent
Requires-Python: >=3.6
License-File: LICENSE
